[{
    "id": 1,
    "title": "black pants ",
    "new": true,
    "folder":"",
    "image": "/images/products/p1.jpg",
    "price": 150,
    "gender": "male"
},
{
    "id": 2,
    "title": "purple pants ",
    "new": false,
    "folder":"",
    "image": "/images/products/p1.jpg",
    "price": 185,
    "gender": "male"
},
{
    "id": 3,
    "title": "orange pants ",
    "new": true,
    "folder":"",
    "image": "/images/products/p1.jpg",
    "price": 256,
    "gender": "male"
},
{
    "id": 4,
    "title": "green pants ",
    "new": true,
    "folder":"",
    "image": "/images/products/p2.jpg",
    "price": 120,
    "gender": "female"
},
{
    "id": 5,
    "title": "red pants ",
    "new": false,
    "folder":"",
    "image": "/images/products/p1.jpg",
    "price": 70,
    "gender": "female"
},
{
    "id": 6,
    "title": "yellow pants ",
    "new": true,
    "folder":"",
    "image": "/images/products/p1.jpg",
    "price": 25,
    "gender": "female"
}

]